{
  "manifestVersion": "3.2",
  "admin": {
    "address": "0xe2b854283bD4A768e71A6f23402D3384317aB1cA",
    "txHash": "0x5c6623911cb029e81610160df00c1b107e4cbadd6581ac572f36b35ee4343d51"
  },
  "proxies": [
    {
      "address": "0x96d4Db7A0FcB5Ba0FA8D35C8E820225A0F8b5c3a",
      "txHash": "0x89e2fda12eb97fe453e1798c6363b7cc87d53dc647f14cb3f601ffea4ecaa267",
      "kind": "transparent"
    }
  ],
  "impls": {
    "2db78483b4123e63496e7e16301bf4bc1007065bad1c6dcdf8473c3e3267ae43": {
      "address": "0x45664Fd4fEd7E3EBF166514a3152db230B647f27",
      "txHash": "0xc3fc3ad2aa7f8063b6095ff3b7091f36164241a97816e1484e3d1d712a621f77",
      "layout": {
        "solcVersion": "0.8.20",
        "storage": [
          {
            "label": "numSodas",
            "offset": 0,
            "slot": "0",
            "type": "t_uint256",
            "contract": "VendingMachineV1",
            "src": "contracts/VendingMachineV1.sol:9"
          },
          {
            "label": "owner",
            "offset": 0,
            "slot": "1",
            "type": "t_address",
            "contract": "VendingMachineV1",
            "src": "contracts/VendingMachineV1.sol:10"
          }
        ],
        "types": {
          "t_address": {
            "label": "address",
            "numberOfBytes": "20"
          },
          "t_uint256": {
            "label": "uint256",
            "numberOfBytes": "32"
          },
          "t_uint64": {
            "label": "uint64"
          },
          "t_bool": {
            "label": "bool"
          }
        },
        "namespaces": {
          "erc7201:openzeppelin.storage.Initializable": [
            {
              "contract": "Initializable",
              "label": "_initialized",
              "type": "t_uint64",
              "src": "@openzeppelin/contracts-upgradeable/proxy/utils/Initializable.sol:69"
            },
            {
              "contract": "Initializable",
              "label": "_initializing",
              "type": "t_bool",
              "src": "@openzeppelin/contracts-upgradeable/proxy/utils/Initializable.sol:73"
            }
          ]
        }
      }
    },
    "82e61094c6dc3a0e5685ea4bba295f6576175dcd842cda2f40739ca70529fc1a": {
      "address": "0xd31E695Bc631760dF4f0dbea059C7745cAFD9EE6",
      "txHash": "0xfcb2a8b64e5951e396a79c8d1d958153305d0ef63a20dfdec20ef837d89a3b00",
      "layout": {
        "solcVersion": "0.8.20",
        "storage": [
          {
            "label": "numSodas",
            "offset": 0,
            "slot": "0",
            "type": "t_uint256",
            "contract": "VendingMachineV2",
            "src": "contracts/VendingMachineV2.sol:9"
          },
          {
            "label": "owner",
            "offset": 0,
            "slot": "1",
            "type": "t_address",
            "contract": "VendingMachineV2",
            "src": "contracts/VendingMachineV2.sol:10"
          }
        ],
        "types": {
          "t_address": {
            "label": "address",
            "numberOfBytes": "20"
          },
          "t_uint256": {
            "label": "uint256",
            "numberOfBytes": "32"
          },
          "t_uint64": {
            "label": "uint64"
          },
          "t_bool": {
            "label": "bool"
          }
        },
        "namespaces": {
          "erc7201:openzeppelin.storage.Initializable": [
            {
              "contract": "Initializable",
              "label": "_initialized",
              "type": "t_uint64",
              "src": "@openzeppelin/contracts-upgradeable/proxy/utils/Initializable.sol:69"
            },
            {
              "contract": "Initializable",
              "label": "_initializing",
              "type": "t_bool",
              "src": "@openzeppelin/contracts-upgradeable/proxy/utils/Initializable.sol:73"
            }
          ]
        }
      }
    }
  }
}
